README.txt
setup.cfg
setup.py
ibmdb2/__init__.py
ibmdb2.egg-info/PKG-INFO
ibmdb2.egg-info/SOURCES.txt
ibmdb2.egg-info/dependency_links.txt
ibmdb2.egg-info/requires.txt
ibmdb2.egg-info/top_level.txt