Metadata-Version: 1.2
Name: ibmdb2
Version: 0.3
Summary: IBM-DB2 Wrapper Class
Home-page: https://github.com/ipal0/ibmdb2
Author: Pal
Author-email: ipal00@outlook.com
License: GPL
Platform: UNKNOWN
Requires-Python: >=3
